{"id":"tt0098936","title":"Twin Peaks","votes":245550,"seasons":{"1":{"1":{"r":8.9,"v":20196},"6":{"r":8.4,"v":7318},"7":{"r":8.4,"v":7136},"4":{"r":8.2,"v":7779},"8":{"r":9.0,"v":7954},"5":{"r":8.1,"v":7433},"2":{"r":8.2,"v":8792},"3":{"r":8.9,"v":9343}},"2":{"9":{"r":9.3,"v":7910},"22":{"r":9.3,"v":8416},"13":{"r":7.5,"v":5381},"2":{"r":8.5,"v":6590},"6":{"r":8.4,"v":6091},"10":{"r":7.7,"v":5643},"14":{"r":7.4,"v":5304},"8":{"r":8.5,"v":6113},"4":{"r":8.0,"v":6074},"7":{"r":9.4,"v":9136},"11":{"r":7.2,"v":5542},"1":{"r":8.9,"v":7772},"21":{"r":8.5,"v":5458},"18":{"r":7.8,"v":5238},"15":{"r":7.1,"v":5323},"12":{"r":7.3,"v":5399},"16":{"r":7.6,"v":5267},"3":{"r":8.1,"v":6154},"5":{"r":8.3,"v":6066},"20":{"r":8.1,"v":5235},"19":{"r":7.8,"v":5148},"17":{"r":7.2,"v":5177}}}}