{"id":"tt0118401","title":"Midsomer Murders","votes":44196,"seasons":{"2":{"4":{"r":7.4,"v":1324},"3":{"r":7.9,"v":1454},"1":{"r":8.2,"v":1637},"2":{"r":7.9,"v":1497}},"1":{"1":{"r":8.2,"v":2654},"5":{"r":7.3,"v":1461},"3":{"r":7.3,"v":1667},"4":{"r":7.5,"v":1521},"2":{"r":7.8,"v":1938}},"6":{"5":{"r":7.5,"v":1016},"4":{"r":7.3,"v":1078},"1":{"r":7.6,"v":1151},"2":{"r":7.7,"v":1262},"3":{"r":8.1,"v":1208}},"4":{"5":{"r":7.5,"v":1199},"2":{"r":7.9,"v":1334},"1":{"r":7.6,"v":1333},"6":{"r":7.6,"v":1173},"3":{"r":7.2,"v":1228},"4":{"r":7.1,"v":1126}},"3":{"1":{"r":7.5,"v":1255},"4":{"r":7.6,"v":1220},"2":{"r":7.5,"v":1295},"3":{"r":8.2,"v":1612}},"5":{"2":{"r":7.4,"v":1098},"1":{"r":7.8,"v":1243},"4":{"r":7.6,"v":1179},"3":{"r":7.8,"v":1304}},"7":{"2":{"r":7.5,"v":1059},"7":{"r":8.3,"v":1365},"4":{"r":7.6,"v":1078},"3":{"r":7.3,"v":1110},"1":{"r":8.1,"v":1340},"5":{"r":7.6,"v":1054},"6":{"r":7.2,"v":1120}},"8":{"4":{"r":7.4,"v":955},"2":{"r":7.5,"v":1023},"6":{"r":8.1,"v":1127},"8":{"r":7.4,"v":1036},"3":{"r":7.6,"v":1014},"7":{"r":7.6,"v":963},"5":{"r":7.0,"v":1049},"1":{"r":7.3,"v":979}},"9":{"2":{"r":7.6,"v":1053},"4":{"r":7.8,"v":1027},"1":{"r":8.0,"v":1205},"3":{"r":8.1,"v":1109},"5":{"r":7.2,"v":990},"6":{"r":7.9,"v":1096},"7":{"r":7.7,"v":1008},"8":{"r":8.2,"v":1144}},"10":{"1":{"r":7.3,"v":968},"5":{"r":7.6,"v":934},"3":{"r":7.4,"v":1023},"4":{"r":7.5,"v":1130},"2":{"r":7.9,"v":1129},"6":{"r":7.8,"v":1016},"8":{"r":7.5,"v":864},"7":{"r":7.3,"v":870}},"21":{"1":{"r":7.1,"v":796},"2":{"r":7.5,"v":752},"4":{"r":7.3,"v":668},"3":{"r":7.1,"v":707}},"11":{"2":{"r":7.9,"v":1034},"1":{"r":7.4,"v":1021},"3":{"r":7.6,"v":954},"4":{"r":7.5,"v":890},"6":{"r":7.2,"v":839},"7":{"r":7.6,"v":909},"5":{"r":7.0,"v":877}},"22":{"1":{"r":6.6,"v":906},"2":{"r":7.3,"v":735},"3":{"r":8.0,"v":925},"4":{"r":7.3,"v":702},"5":{"r":7.4,"v":721},"6":{"r":6.6,"v":627}},"12":{"3":{"r":7.6,"v":976},"5":{"r":7.8,"v":976},"2":{"r":7.9,"v":979},"6":{"r":7.9,"v":981},"1":{"r":7.5,"v":902},"4":{"r":7.3,"v":855},"7":{"r":7.7,"v":936}},"13":{"2":{"r":7.3,"v":950},"1":{"r":7.7,"v":1036},"3":{"r":6.3,"v":1022},"4":{"r":7.3,"v":924},"5":{"r":7.9,"v":1067},"6":{"r":7.2,"v":873},"7":{"r":7.3,"v":825},"8":{"r":7.8,"v":932}},"14":{"2":{"r":7.9,"v":1037},"3":{"r":7.3,"v":967},"1":{"r":7.4,"v":1039},"4":{"r":7.7,"v":929},"5":{"r":7.3,"v":811},"6":{"r":6.4,"v":919},"8":{"r":7.4,"v":788},"7":{"r":7.7,"v":855}},"15":{"1":{"r":7.5,"v":921},"2":{"r":7.6,"v":838},"3":{"r":7.0,"v":810},"5":{"r":7.4,"v":856},"6":{"r":7.6,"v":863},"4":{"r":7.5,"v":907}},"23":{"1":{"r":6.8,"v":707},"2":{"r":7.3,"v":585},"3":{"r":7.0,"v":577},"4":{"r":6.0,"v":933}},"16":{"2":{"r":7.3,"v":829},"3":{"r":7.8,"v":877},"1":{"r":7.5,"v":889},"4":{"r":7.4,"v":791},"5":{"r":7.8,"v":973}},"24":{"1":{"r":7.2,"v":599},"2":{"r":7.0,"v":517},"3":{"r":6.9,"v":435},"4":{"r":6.7,"v":466}},"25":{"1":{"r":7.2,"v":288},"2":{"r":7.2,"v":248},"3":{"r":7.2,"v":215},"4":{"r":7.7,"v":177}},"17":{"1":{"r":7.3,"v":815},"3":{"r":7.5,"v":891},"2":{"r":7.3,"v":838},"4":{"r":7.8,"v":878}},"18":{"1":{"r":7.4,"v":837},"2":{"r":7.2,"v":815},"3":{"r":6.7,"v":799},"4":{"r":7.3,"v":776},"5":{"r":7.2,"v":757},"6":{"r":7.4,"v":708}},"19":{"1":{"r":7.5,"v":882},"2":{"r":7.4,"v":787},"3":{"r":7.8,"v":907},"4":{"r":7.2,"v":767},"5":{"r":7.1,"v":820},"6":{"r":7.3,"v":725}},"20":{"1":{"r":7.2,"v":870},"2":{"r":7.3,"v":850},"3":{"r":7.3,"v":796},"4":{"r":7.2,"v":776},"5":{"r":7.5,"v":741},"6":{"r":7.0,"v":675}}}}