{"id":"tt0297512","title":"The Brak Show","votes":4447,"seasons":{"3":{"1":{"r":7.7,"v":34},"5":{"r":6.7,"v":35},"3":{"r":8.1,"v":44},"7":{"r":6.9,"v":33},"8":{"r":7.7,"v":32},"2":{"r":6.7,"v":35},"6":{"r":7.2,"v":35},"4":{"r":7.3,"v":37}},"2":{"5":{"r":7.6,"v":32},"6":{"r":7.3,"v":37},"7":{"r":8.0,"v":37},"10":{"r":7.9,"v":35},"3":{"r":7.2,"v":36},"9":{"r":7.1,"v":33},"1":{"r":7.1,"v":37},"4":{"r":7.3,"v":38},"8":{"r":7.1,"v":34},"11":{"r":8.0,"v":34},"2":{"r":7.7,"v":36}},"1":{"7":{"r":7.2,"v":41},"2":{"r":7.6,"v":68},"5":{"r":7.4,"v":45},"6":{"r":6.5,"v":49},"1":{"r":6.9,"v":61},"8":{"r":7.9,"v":50},"9":{"r":7.7,"v":45},"3":{"r":8.3,"v":64},"4":{"r":7.8,"v":55}},"0":{"0":{"r":7.6,"v":11}}}}