{"id":"tt0278877","title":"Sealab 2021","votes":8690,"seasons":{"1":{"9":{"r":7.8,"v":138},"4":{"r":7.5,"v":131},"3":{"r":7.9,"v":153},"2":{"r":7.4,"v":172},"7":{"r":6.9,"v":116},"10":{"r":7.6,"v":119},"5":{"r":7.0,"v":122},"1":{"r":7.2,"v":178},"8":{"r":7.0,"v":120},"6":{"r":7.6,"v":130},"0":{"r":6.2,"v":64}},"3":{"4":{"r":7.1,"v":71},"1":{"r":7.0,"v":76},"3":{"r":7.4,"v":87},"9":{"r":6.2,"v":70},"5":{"r":6.9,"v":72},"2":{"r":6.6,"v":91},"11":{"r":7.4,"v":65},"10":{"r":6.9,"v":73},"8":{"r":7.2,"v":64},"6":{"r":6.5,"v":67},"12":{"r":6.0,"v":62},"7":{"r":6.6,"v":64}},"2":{"7":{"r":8.1,"v":156},"11":{"r":7.4,"v":102},"3":{"r":7.2,"v":108},"9":{"r":7.2,"v":102},"10":{"r":5.4,"v":114},"4":{"r":7.5,"v":106},"6":{"r":7.6,"v":105},"1":{"r":7.7,"v":116},"8":{"r":6.7,"v":96},"5":{"r":7.7,"v":96},"2":{"r":8.2,"v":138}},"5":{"1":{"r":6.3,"v":59},"2":{"r":6.9,"v":59},"5":{"r":6.6,"v":56},"8":{"r":6.4,"v":56},"6":{"r":6.6,"v":57},"3":{"r":6.8,"v":60},"7":{"r":6.8,"v":54},"4":{"r":7.0,"v":59}},"4":{"8":{"r":6.8,"v":61},"11":{"r":6.7,"v":58},"10":{"r":6.4,"v":59},"4":{"r":6.7,"v":63},"1":{"r":6.6,"v":63},"2":{"r":6.1,"v":59},"3":{"r":5.9,"v":63},"9":{"r":6.7,"v":60},"7":{"r":6.9,"v":57},"5":{"r":6.7,"v":58},"6":{"r":6.8,"v":55}}}}