{"id":"tt0397306","title":"American Dad!","votes":144004,"seasons":{"1":{"9":{"r":7.7,"v":1189},"10":{"r":7.3,"v":1093},"8":{"r":7.7,"v":1207},"11":{"r":7.1,"v":1056},"7":{"r":7.2,"v":1160},"18":{"r":7.4,"v":1004},"4":{"r":7.3,"v":1302},"6":{"r":7.5,"v":1256},"16":{"r":7.2,"v":1088},"1":{"r":7.2,"v":1640},"5":{"r":7.5,"v":1214},"17":{"r":7.5,"v":1066},"3":{"r":7.2,"v":1300},"12":{"r":7.7,"v":1206},"13":{"r":7.7,"v":1175},"14":{"r":7.4,"v":1058},"15":{"r":7.3,"v":1034},"2":{"r":7.1,"v":1338},"19":{"r":7.1,"v":1050},"20":{"r":7.6,"v":1002},"21":{"r":7.1,"v":979},"22":{"r":7.7,"v":1066},"23":{"r":7.6,"v":1093}},"2":{"1":{"r":7.7,"v":1124},"5":{"r":7.6,"v":997},"3":{"r":7.5,"v":1004},"6":{"r":7.3,"v":992},"4":{"r":7.7,"v":1054},"2":{"r":7.9,"v":1171},"8":{"r":7.2,"v":977},"7":{"r":7.1,"v":934},"9":{"r":7.9,"v":1079},"10":{"r":7.4,"v":947},"11":{"r":7.3,"v":900},"12":{"r":7.2,"v":954},"13":{"r":7.8,"v":967},"14":{"r":7.5,"v":932},"15":{"r":7.6,"v":896},"17":{"r":7.4,"v":894},"16":{"r":7.5,"v":882},"19":{"r":8.0,"v":1013},"18":{"r":7.3,"v":831}},"3":{"7":{"r":7.4,"v":906},"16":{"r":7.8,"v":961},"1":{"r":8.2,"v":1154},"2":{"r":7.8,"v":986},"4":{"r":7.3,"v":894},"9":{"r":7.5,"v":895},"5":{"r":7.4,"v":903},"10":{"r":8.4,"v":1283},"6":{"r":7.4,"v":897},"11":{"r":7.2,"v":876},"13":{"r":7.3,"v":850},"12":{"r":7.6,"v":867},"3":{"r":8.1,"v":1077},"8":{"r":7.9,"v":999},"14":{"r":7.7,"v":884},"15":{"r":7.4,"v":846}},"4":{"2":{"r":7.9,"v":1025},"7":{"r":7.7,"v":928},"5":{"r":7.6,"v":933},"1":{"r":7.8,"v":964},"4":{"r":7.4,"v":835},"6":{"r":7.3,"v":849},"3":{"r":6.9,"v":795},"10":{"r":7.2,"v":804},"11":{"r":7.2,"v":809},"12":{"r":7.6,"v":942},"13":{"r":7.1,"v":768},"15":{"r":7.6,"v":851},"16":{"r":7.3,"v":827},"17":{"r":7.0,"v":782},"18":{"r":7.5,"v":815},"19":{"r":7.2,"v":771},"20":{"r":7.4,"v":815},"8":{"r":7.1,"v":809},"9":{"r":7.3,"v":822},"14":{"r":7.5,"v":855}},"14":{"2":{"r":6.7,"v":510},"3":{"r":7.5,"v":521},"4":{"r":8.7,"v":1282},"5":{"r":7.4,"v":573},"6":{"r":6.6,"v":466},"7":{"r":7.2,"v":498},"8":{"r":7.1,"v":469},"9":{"r":6.7,"v":478},"10":{"r":6.8,"v":482},"11":{"r":6.4,"v":463},"12":{"r":7.0,"v":488},"13":{"r":6.7,"v":469},"14":{"r":6.5,"v":481},"15":{"r":6.7,"v":466},"16":{"r":7.1,"v":460},"17":{"r":7.7,"v":543},"18":{"r":7.4,"v":489},"19":{"r":7.2,"v":484},"20":{"r":7.3,"v":480},"1":{"r":7.0,"v":495}},"15":{"3":{"r":6.2,"v":516},"1":{"r":6.9,"v":600},"4":{"r":6.7,"v":664},"5":{"r":6.3,"v":513},"6":{"r":6.7,"v":510},"7":{"r":6.7,"v":471},"10":{"r":6.5,"v":456},"8":{"r":6.8,"v":456},"9":{"r":7.4,"v":487},"11":{"r":7.4,"v":524},"12":{"r":6.5,"v":447},"13":{"r":6.6,"v":528},"14":{"r":7.0,"v":439},"15":{"r":7.1,"v":471},"16":{"r":7.3,"v":484},"2":{"r":7.2,"v":524},"17":{"r":7.0,"v":440},"18":{"r":7.0,"v":416},"19":{"r":6.5,"v":416},"20":{"r":6.4,"v":419},"21":{"r":6.5,"v":417},"22":{"r":6.7,"v":424},"23":{"r":8.0,"v":571},"24":{"r":7.7,"v":485}},"16":{"1":{"r":7.2,"v":468},"2":{"r":7.1,"v":469},"3":{"r":6.5,"v":626},"4":{"r":6.9,"v":432},"5":{"r":5.9,"v":518},"6":{"r":7.1,"v":425},"7":{"r":7.5,"v":446},"8":{"r":7.0,"v":414},"9":{"r":6.7,"v":396},"10":{"r":7.3,"v":420},"11":{"r":6.5,"v":448},"16":{"r":6.7,"v":384},"12":{"r":7.0,"v":398},"13":{"r":7.6,"v":440},"14":{"r":7.0,"v":401},"15":{"r":6.1,"v":400},"17":{"r":7.0,"v":369},"18":{"r":7.1,"v":381},"19":{"r":6.9,"v":373},"20":{"r":6.5,"v":356},"21":{"r":6.8,"v":352},"22":{"r":6.5,"v":364}},"5":{"3":{"r":7.3,"v":803},"1":{"r":8.2,"v":1141},"2":{"r":7.6,"v":872},"4":{"r":7.3,"v":779},"5":{"r":7.2,"v":888},"6":{"r":7.2,"v":847},"8":{"r":7.3,"v":807},"7":{"r":7.4,"v":917},"9":{"r":8.8,"v":1969},"10":{"r":7.5,"v":775},"11":{"r":8.0,"v":928},"13":{"r":7.5,"v":795},"12":{"r":7.4,"v":802},"14":{"r":7.6,"v":830},"15":{"r":7.7,"v":805},"17":{"r":7.1,"v":784},"16":{"r":7.6,"v":852},"18":{"r":8.2,"v":940}},"17":{"1":{"r":6.8,"v":668},"9":{"r":7.1,"v":631},"14":{"r":6.5,"v":534},"2":{"r":7.1,"v":638},"3":{"r":6.7,"v":606},"4":{"r":6.7,"v":613},"5":{"r":6.5,"v":612},"6":{"r":6.3,"v":619},"7":{"r":6.8,"v":620},"8":{"r":6.9,"v":626},"10":{"r":7.6,"v":826},"11":{"r":6.7,"v":629},"12":{"r":7.2,"v":654},"13":{"r":7.0,"v":588},"15":{"r":6.3,"v":436},"16":{"r":6.9,"v":404},"17":{"r":6.4,"v":376},"18":{"r":6.6,"v":346},"19":{"r":6.6,"v":354},"20":{"r":6.3,"v":355},"21":{"r":6.8,"v":371},"22":{"r":6.3,"v":383}},"6":{"1":{"r":7.7,"v":878},"10":{"r":7.6,"v":812},"11":{"r":7.3,"v":779},"12":{"r":7.4,"v":768},"13":{"r":7.6,"v":771},"14":{"r":7.4,"v":769},"15":{"r":7.1,"v":742},"16":{"r":7.3,"v":761},"17":{"r":7.3,"v":749},"19":{"r":6.9,"v":744},"2":{"r":7.7,"v":858},"3":{"r":7.7,"v":894},"4":{"r":7.4,"v":819},"5":{"r":7.1,"v":777},"6":{"r":7.5,"v":822},"7":{"r":7.6,"v":814},"8":{"r":8.6,"v":1297},"9":{"r":7.4,"v":800},"18":{"r":7.3,"v":748}},"7":{"2":{"r":8.2,"v":1138},"1":{"r":7.4,"v":1403},"10":{"r":7.3,"v":732},"11":{"r":7.6,"v":773},"12":{"r":7.1,"v":696},"13":{"r":7.5,"v":712},"14":{"r":6.8,"v":815},"15":{"r":7.6,"v":769},"16":{"r":7.6,"v":739},"17":{"r":7.8,"v":987},"18":{"r":7.2,"v":702},"3":{"r":7.1,"v":763},"4":{"r":7.0,"v":789},"5":{"r":7.9,"v":885},"6":{"r":7.3,"v":746},"7":{"r":7.9,"v":877},"8":{"r":7.3,"v":706},"9":{"r":7.4,"v":737}},"8":{"1":{"r":7.4,"v":879},"9":{"r":7.4,"v":719},"2":{"r":7.7,"v":905},"3":{"r":7.7,"v":834},"4":{"r":7.5,"v":760},"5":{"r":7.2,"v":774},"6":{"r":7.6,"v":772},"7":{"r":6.6,"v":745},"8":{"r":7.1,"v":727},"10":{"r":6.8,"v":1036},"11":{"r":7.3,"v":755},"12":{"r":7.5,"v":729},"13":{"r":7.2,"v":808},"15":{"r":7.1,"v":712},"17":{"r":7.1,"v":665},"16":{"r":6.8,"v":694},"18":{"r":8.5,"v":1295},"19":{"r":7.5,"v":725},"14":{"r":7.4,"v":722}},"9":{"8":{"r":7.8,"v":1179},"1":{"r":7.6,"v":887},"2":{"r":7.4,"v":911},"4":{"r":7.2,"v":803},"3":{"r":7.3,"v":788},"19":{"r":7.3,"v":690},"16":{"r":7.3,"v":705},"5":{"r":6.6,"v":808},"6":{"r":7.2,"v":1061},"7":{"r":8.0,"v":949},"9":{"r":7.8,"v":838},"10":{"r":7.8,"v":902},"11":{"r":7.2,"v":743},"12":{"r":7.0,"v":744},"13":{"r":7.2,"v":719},"14":{"r":7.2,"v":738},"15":{"r":6.9,"v":692},"17":{"r":7.0,"v":813},"18":{"r":7.3,"v":690},"20":{"r":7.3,"v":700},"21":{"r":7.1,"v":686},"22":{"r":7.3,"v":718},"23":{"r":7.0,"v":725}},"18":{"1":{"r":7.6,"v":637},"2":{"r":6.7,"v":520},"3":{"r":6.7,"v":496},"4":{"r":6.5,"v":498},"5":{"r":6.1,"v":485},"6":{"r":6.4,"v":474},"7":{"r":6.2,"v":498},"8":{"r":6.3,"v":465},"9":{"r":6.6,"v":472},"10":{"r":7.2,"v":447},"11":{"r":7.3,"v":451},"12":{"r":7.2,"v":461},"13":{"r":6.8,"v":459},"14":{"r":7.6,"v":508},"15":{"r":7.5,"v":464},"16":{"r":6.5,"v":353},"17":{"r":7.7,"v":443},"18":{"r":6.9,"v":332},"19":{"r":7.3,"v":356},"20":{"r":6.7,"v":330},"21":{"r":6.9,"v":317},"22":{"r":7.0,"v":335}},"19":{"1":{"r":7.6,"v":393},"2":{"r":6.7,"v":326},"3":{"r":7.1,"v":323},"4":{"r":7.1,"v":305},"5":{"r":6.7,"v":288},"6":{"r":6.5,"v":292},"7":{"r":6.0,"v":287},"8":{"r":6.5,"v":272},"9":{"r":7.0,"v":268},"10":{"r":6.6,"v":253},"11":{"r":6.9,"v":272},"12":{"r":7.1,"v":267},"13":{"r":8.0,"v":388},"14":{"r":6.6,"v":269},"15":{"r":7.0,"v":247},"16":{"r":6.9,"v":247},"17":{"r":6.6,"v":233},"18":{"r":6.8,"v":228},"19":{"r":6.8,"v":250},"20":{"r":6.0,"v":268},"21":{"r":6.7,"v":237},"22":{"r":7.3,"v":299}},"20":{"1":{"r":7.2,"v":189},"2":{"r":6.7,"v":145},"4":{"r":7.0,"v":102},"3":{"r":7.7,"v":138}},"10":{"1":{"r":7.2,"v":688},"6":{"r":7.3,"v":696},"2":{"r":6.9,"v":920},"3":{"r":6.8,"v":659},"4":{"r":6.9,"v":798},"5":{"r":7.4,"v":653},"7":{"r":7.4,"v":708},"8":{"r":7.4,"v":666},"9":{"r":7.1,"v":756},"10":{"r":7.0,"v":661},"11":{"r":7.1,"v":628},"12":{"r":7.4,"v":634},"13":{"r":7.6,"v":653},"14":{"r":4.0,"v":1758},"15":{"r":6.7,"v":696}},"11":{"1":{"r":7.0,"v":630},"15":{"r":7.3,"v":596},"13":{"r":7.0,"v":566},"18":{"r":7.3,"v":594},"16":{"r":7.1,"v":578},"2":{"r":7.3,"v":645},"3":{"r":7.3,"v":592},"4":{"r":7.0,"v":578},"5":{"r":7.0,"v":571},"11":{"r":8.1,"v":719},"6":{"r":6.8,"v":548},"7":{"r":7.1,"v":544},"8":{"r":7.1,"v":552},"10":{"r":8.6,"v":1041},"9":{"r":7.3,"v":564},"12":{"r":7.2,"v":578},"14":{"r":7.1,"v":545},"17":{"r":7.5,"v":734},"19":{"r":7.0,"v":536},"20":{"r":7.4,"v":538},"21":{"r":7.4,"v":536},"22":{"r":7.0,"v":519}},"12":{"1":{"r":7.5,"v":634},"2":{"r":6.7,"v":558},"4":{"r":6.8,"v":585},"3":{"r":6.8,"v":561},"5":{"r":7.3,"v":544},"6":{"r":7.2,"v":554},"7":{"r":7.3,"v":580},"9":{"r":7.2,"v":571},"8":{"r":6.9,"v":555},"10":{"r":6.9,"v":535},"11":{"r":6.9,"v":598},"12":{"r":6.6,"v":509},"13":{"r":6.6,"v":505},"14":{"r":7.1,"v":685},"15":{"r":7.3,"v":614},"16":{"r":6.8,"v":547},"17":{"r":6.6,"v":539},"18":{"r":7.0,"v":536},"19":{"r":6.7,"v":664},"21":{"r":7.6,"v":546},"22":{"r":7.3,"v":539},"20":{"r":6.7,"v":497}},"13":{"2":{"r":7.2,"v":559},"1":{"r":6.5,"v":555},"3":{"r":6.8,"v":518},"4":{"r":7.0,"v":581},"5":{"r":6.7,"v":510},"6":{"r":6.9,"v":501},"7":{"r":6.9,"v":506},"8":{"r":7.7,"v":565},"9":{"r":6.8,"v":499},"10":{"r":6.7,"v":480},"11":{"r":7.3,"v":536},"12":{"r":7.7,"v":533},"13":{"r":6.8,"v":491},"14":{"r":6.8,"v":494},"15":{"r":6.3,"v":511},"16":{"r":8.2,"v":657},"17":{"r":6.9,"v":473},"18":{"r":6.9,"v":461},"19":{"r":7.4,"v":519},"20":{"r":7.1,"v":438},"21":{"r":6.8,"v":451},"22":{"r":7.0,"v":438}}}}