{"id":"tt0773262","title":"Dexter","votes":931362,"seasons":{"1":{"2":{"r":8.1,"v":16294},"1":{"r":8.7,"v":22749},"5":{"r":8.4,"v":14318},"4":{"r":8.6,"v":14876},"3":{"r":8.2,"v":15265},"6":{"r":8.9,"v":15405},"7":{"r":8.6,"v":14052},"8":{"r":8.9,"v":15483},"9":{"r":8.5,"v":13860},"10":{"r":9.1,"v":15893},"11":{"r":9.3,"v":16938},"12":{"r":9.6,"v":30488}},"2":{"1":{"r":8.6,"v":13018},"10":{"r":8.9,"v":12508},"11":{"r":9.0,"v":12727},"12":{"r":9.2,"v":15474},"2":{"r":8.4,"v":12067},"3":{"r":8.5,"v":11962},"4":{"r":8.2,"v":11602},"5":{"r":8.6,"v":11922},"6":{"r":8.5,"v":11631},"7":{"r":8.7,"v":11817},"8":{"r":9.1,"v":12825},"9":{"r":9.5,"v":16770}},"3":{"1":{"r":8.1,"v":11005},"10":{"r":9.0,"v":11234},"11":{"r":8.9,"v":10869},"12":{"r":8.8,"v":11604},"2":{"r":8.3,"v":10530},"3":{"r":8.0,"v":10415},"4":{"r":8.0,"v":10350},"5":{"r":8.3,"v":10153},"6":{"r":8.1,"v":10042},"7":{"r":8.4,"v":10302},"8":{"r":8.5,"v":10119},"9":{"r":8.7,"v":10342}},"4":{"1":{"r":8.6,"v":11465},"10":{"r":9.2,"v":13317},"11":{"r":9.5,"v":18113},"12":{"r":9.8,"v":42981},"2":{"r":8.6,"v":10625},"3":{"r":8.2,"v":10421},"4":{"r":9.2,"v":12429},"5":{"r":9.0,"v":11422},"6":{"r":8.6,"v":10471},"7":{"r":8.4,"v":10323},"8":{"r":8.4,"v":10507},"9":{"r":9.5,"v":15833}},"5":{"1":{"r":8.9,"v":12764},"2":{"r":8.1,"v":9366},"4":{"r":8.2,"v":9065},"3":{"r":8.3,"v":9112},"5":{"r":7.8,"v":9695},"6":{"r":8.7,"v":9634},"8":{"r":8.8,"v":9415},"7":{"r":8.2,"v":8937},"12":{"r":8.8,"v":10885},"11":{"r":8.8,"v":9377},"10":{"r":8.9,"v":9767},"9":{"r":8.9,"v":9867}},"6":{"1":{"r":8.3,"v":10302},"10":{"r":7.9,"v":8956},"11":{"r":8.2,"v":8925},"12":{"r":9.1,"v":13580},"2":{"r":7.9,"v":9448},"3":{"r":8.0,"v":8895},"4":{"r":8.3,"v":8911},"5":{"r":7.8,"v":8988},"6":{"r":8.4,"v":9225},"7":{"r":7.8,"v":10757},"8":{"r":7.7,"v":8842},"9":{"r":8.4,"v":9347}},"7":{"1":{"r":9.4,"v":19118},"3":{"r":8.5,"v":9260},"5":{"r":8.4,"v":8824},"6":{"r":8.1,"v":8952},"4":{"r":8.8,"v":10255},"8":{"r":8.8,"v":10221},"7":{"r":8.3,"v":8869},"10":{"r":8.3,"v":8637},"9":{"r":8.6,"v":8963},"12":{"r":9.3,"v":14948},"11":{"r":8.9,"v":9664},"2":{"r":8.7,"v":9908}},"8":{"1":{"r":8.4,"v":11528},"2":{"r":7.8,"v":9393},"3":{"r":7.9,"v":9210},"4":{"r":7.9,"v":9256},"5":{"r":7.7,"v":9014},"6":{"r":7.6,"v":9005},"7":{"r":7.4,"v":9097},"8":{"r":7.9,"v":9673},"9":{"r":7.2,"v":9408},"10":{"r":6.9,"v":10487},"11":{"r":7.2,"v":10636},"12":{"r":4.9,"v":33926}}}}