{"id":"tt0760437","title":"Ben 10","votes":35731,"seasons":{"1":{"1":{"r":8.2,"v":1969},"11":{"r":7.4,"v":983},"5":{"r":8.2,"v":1170},"7":{"r":8.4,"v":1196},"9":{"r":8.0,"v":1067},"10":{"r":7.7,"v":1011},"4":{"r":7.3,"v":1185},"13":{"r":9.0,"v":1237},"12":{"r":7.0,"v":978},"8":{"r":7.5,"v":1013},"3":{"r":7.3,"v":1250},"6":{"r":6.9,"v":1065},"2":{"r":7.3,"v":1245}},"2":{"7":{"r":7.6,"v":895},"3":{"r":8.6,"v":1008},"5":{"r":8.3,"v":949},"4":{"r":7.6,"v":953},"2":{"r":7.2,"v":923},"6":{"r":7.2,"v":880},"1":{"r":7.7,"v":960},"9":{"r":7.7,"v":868},"11":{"r":8.6,"v":1000},"10":{"r":7.3,"v":855},"8":{"r":7.4,"v":869},"12":{"r":7.6,"v":857},"13":{"r":9.1,"v":1235}},"3":{"5":{"r":8.5,"v":945},"1":{"r":8.9,"v":1201},"8":{"r":7.8,"v":811},"3":{"r":7.8,"v":838},"4":{"r":6.8,"v":821},"2":{"r":7.2,"v":818},"6":{"r":8.1,"v":873},"7":{"r":6.8,"v":801},"9":{"r":7.3,"v":756},"10":{"r":7.0,"v":763},"11":{"r":8.2,"v":832},"13":{"r":7.8,"v":807},"12":{"r":8.6,"v":881}},"4":{"2":{"r":7.6,"v":783},"1":{"r":8.1,"v":829},"3":{"r":7.5,"v":763},"4":{"r":7.6,"v":774},"6":{"r":7.1,"v":751},"7":{"r":8.6,"v":857},"9":{"r":8.2,"v":793},"10":{"r":8.1,"v":785},"5":{"r":6.5,"v":754},"8":{"r":8.2,"v":782},"11":{"r":8.9,"v":801},"12":{"r":8.9,"v":767},"13":{"r":9.4,"v":1195}}}}