{"id":"tt0813715","title":"Heroes","votes":259636,"seasons":{"1":{"1":{"r":8.1,"v":3316},"3":{"r":8.0,"v":2359},"2":{"r":8.0,"v":2553},"4":{"r":8.1,"v":2267},"5":{"r":8.1,"v":2206},"7":{"r":7.8,"v":2048},"6":{"r":7.7,"v":2091},"9":{"r":8.6,"v":2279},"8":{"r":7.9,"v":2070},"10":{"r":8.3,"v":2138},"12":{"r":7.9,"v":2014},"13":{"r":7.8,"v":1960},"11":{"r":8.4,"v":2073},"14":{"r":8.1,"v":1983},"15":{"r":7.9,"v":1972},"16":{"r":8.3,"v":2034},"17":{"r":8.9,"v":2692},"18":{"r":8.5,"v":2215},"19":{"r":8.3,"v":2107},"23":{"r":8.4,"v":2857},"22":{"r":8.4,"v":2027},"20":{"r":9.0,"v":2986},"21":{"r":8.1,"v":2020},"0":{"r":8.2,"v":1090}},"2":{"1":{"r":7.7,"v":2249},"10":{"r":7.6,"v":1502},"11":{"r":7.9,"v":1703},"2":{"r":7.6,"v":1723},"3":{"r":7.5,"v":1675},"4":{"r":7.5,"v":1533},"5":{"r":7.6,"v":1594},"6":{"r":7.3,"v":1480},"7":{"r":7.8,"v":1540},"8":{"r":7.9,"v":1613},"9":{"r":8.2,"v":1624}},"3":{"12":{"r":7.8,"v":1359},"13":{"r":7.5,"v":1368},"14":{"r":7.6,"v":1332},"15":{"r":7.4,"v":1245},"16":{"r":7.1,"v":1194},"17":{"r":7.0,"v":1154},"18":{"r":7.1,"v":1172},"19":{"r":7.4,"v":1177},"20":{"r":7.8,"v":1328},"21":{"r":7.2,"v":1180},"22":{"r":7.4,"v":1132},"23":{"r":7.2,"v":1246},"1":{"r":7.6,"v":1949},"10":{"r":7.4,"v":1276},"11":{"r":7.4,"v":1279},"2":{"r":7.5,"v":1565},"3":{"r":7.4,"v":1448},"4":{"r":7.5,"v":1463},"5":{"r":7.3,"v":1379},"6":{"r":7.4,"v":1379},"7":{"r":7.2,"v":1276},"8":{"r":7.6,"v":1373},"9":{"r":7.3,"v":1270},"24":{"r":7.4,"v":1055},"25":{"r":7.5,"v":1299}},"4":{"1":{"r":7.4,"v":1230},"2":{"r":7.2,"v":1045},"9":{"r":7.3,"v":956},"10":{"r":7.2,"v":958},"11":{"r":7.2,"v":989},"12":{"r":6.9,"v":942},"13":{"r":6.8,"v":963},"14":{"r":6.9,"v":952},"15":{"r":6.8,"v":1005},"16":{"r":7.2,"v":949},"17":{"r":7.4,"v":989},"3":{"r":7.1,"v":1017},"4":{"r":7.4,"v":1037},"5":{"r":7.3,"v":1009},"6":{"r":7.1,"v":994},"7":{"r":7.5,"v":1048},"8":{"r":7.4,"v":978},"18":{"r":7.6,"v":1349}}}}