{"id":"tt0903747","title":"Breaking Bad","votes":2592666,"seasons":{"1":{"1":{"r":9.0,"v":79360},"2":{"r":8.6,"v":59257},"3":{"r":8.7,"v":57096},"4":{"r":8.2,"v":54922},"5":{"r":8.2,"v":53779},"6":{"r":9.3,"v":62896},"7":{"r":8.8,"v":54804}},"2":{"1":{"r":8.6,"v":49335},"10":{"r":8.4,"v":45732},"11":{"r":8.9,"v":47407},"12":{"r":9.3,"v":53346},"13":{"r":9.2,"v":52163},"2":{"r":9.3,"v":56642},"3":{"r":8.3,"v":47531},"4":{"r":8.2,"v":47628},"5":{"r":8.2,"v":46811},"6":{"r":8.8,"v":50043},"7":{"r":8.6,"v":46674},"8":{"r":9.2,"v":54979},"9":{"r":9.2,"v":52679}},"3":{"1":{"r":8.4,"v":44977},"2":{"r":8.6,"v":44109},"3":{"r":8.3,"v":43758},"10":{"r":7.9,"v":93481},"11":{"r":8.4,"v":43328},"12":{"r":9.5,"v":59818},"13":{"r":9.7,"v":73459},"4":{"r":8.1,"v":45542},"5":{"r":8.5,"v":43017},"6":{"r":9.3,"v":49495},"8":{"r":8.7,"v":44113},"9":{"r":8.3,"v":43412},"7":{"r":9.6,"v":60667}},"4":{"1":{"r":9.2,"v":52387},"10":{"r":9.6,"v":63633},"11":{"r":9.7,"v":81218},"12":{"r":9.5,"v":58737},"13":{"r":9.8,"v":153715},"2":{"r":8.2,"v":44572},"3":{"r":7.9,"v":53681},"4":{"r":8.5,"v":43435},"5":{"r":8.6,"v":43224},"6":{"r":8.4,"v":44201},"7":{"r":8.8,"v":44709},"8":{"r":9.3,"v":50960},"9":{"r":8.9,"v":46511}},"5":{"1":{"r":9.2,"v":61450},"10":{"r":9.2,"v":60663},"11":{"r":9.6,"v":77326},"12":{"r":9.1,"v":65106},"13":{"r":9.7,"v":123520},"14":{"r":9.5,"v":494704},"15":{"r":9.6,"v":118516},"16":{"r":9.8,"v":285969},"2":{"r":8.8,"v":54451},"3":{"r":8.8,"v":53823},"4":{"r":8.7,"v":54231},"5":{"r":9.6,"v":83287},"6":{"r":9.0,"v":56697},"7":{"r":9.6,"v":79036},"8":{"r":9.5,"v":70115},"9":{"r":9.4,"v":65879}}}}