{"id":"tt11280740","title":"Severance","votes":382675,"seasons":{"1":{"1":{"r":8.1,"v":16877},"2":{"r":8.0,"v":14375},"3":{"r":7.7,"v":13653},"4":{"r":8.2,"v":13662},"5":{"r":7.7,"v":13023},"6":{"r":7.9,"v":12853},"7":{"r":8.9,"v":15981},"8":{"r":8.9,"v":15637},"9":{"r":9.7,"v":34282}},"2":{"1":{"r":8.0,"v":15115},"2":{"r":8.2,"v":13548},"3":{"r":8.5,"v":14008},"4":{"r":8.9,"v":19605},"5":{"r":8.0,"v":12214},"6":{"r":8.3,"v":12756},"7":{"r":9.1,"v":23436},"8":{"r":6.6,"v":19670},"9":{"r":8.1,"v":12667},"10":{"r":9.4,"v":31174}}}}