{"id":"tt11691774","title":"Only Murders in the Building","votes":202548,"seasons":{"1":{"1":{"r":7.7,"v":7660},"2":{"r":7.7,"v":6602},"3":{"r":7.8,"v":6263},"4":{"r":8.1,"v":6020},"7":{"r":8.6,"v":7631},"8":{"r":8.2,"v":5330},"5":{"r":7.8,"v":5539},"9":{"r":8.3,"v":5287},"10":{"r":8.8,"v":6095},"6":{"r":7.4,"v":5899}},"2":{"1":{"r":7.8,"v":5039},"2":{"r":7.6,"v":4901},"3":{"r":8.2,"v":4669},"4":{"r":8.1,"v":4394},"5":{"r":7.7,"v":4214},"6":{"r":7.8,"v":4137},"7":{"r":7.9,"v":4222},"8":{"r":7.9,"v":4086},"9":{"r":8.3,"v":4048},"10":{"r":8.9,"v":5597}},"3":{"1":{"r":8.0,"v":4235},"7":{"r":7.6,"v":3189},"2":{"r":7.7,"v":3743},"3":{"r":7.8,"v":3743},"4":{"r":7.5,"v":3516},"5":{"r":7.4,"v":3306},"6":{"r":7.3,"v":3253},"8":{"r":8.7,"v":4132},"9":{"r":8.4,"v":3356},"10":{"r":8.3,"v":3566}},"4":{"1":{"r":8.2,"v":3735},"2":{"r":8.0,"v":3141},"3":{"r":7.5,"v":2946},"4":{"r":7.4,"v":2873},"5":{"r":7.6,"v":2842},"6":{"r":7.8,"v":3150},"7":{"r":7.9,"v":3012},"8":{"r":7.6,"v":2662},"9":{"r":8.0,"v":2552},"10":{"r":8.2,"v":2814}},"5":{"5":{"r":7.6,"v":1834},"1":{"r":7.9,"v":2412},"8":{"r":7.7,"v":1684},"10":{"r":7.7,"v":1713},"3":{"r":7.8,"v":2125},"6":{"r":7.3,"v":1784},"9":{"r":7.4,"v":1621},"4":{"r":7.7,"v":1957},"7":{"r":7.3,"v":1772},"2":{"r":8.4,"v":2518}}}}