{"id":"tt11311302","title":"Vikings: Valhalla","votes":70729,"seasons":{"1":{"2":{"r":7.4,"v":2677},"3":{"r":7.4,"v":2494},"4":{"r":8.4,"v":2999},"1":{"r":7.5,"v":3232},"5":{"r":7.5,"v":2376},"6":{"r":7.3,"v":2352},"7":{"r":7.5,"v":2270},"8":{"r":8.2,"v":2804}},"2":{"1":{"r":7.2,"v":1569},"2":{"r":7.2,"v":1410},"3":{"r":7.2,"v":1339},"4":{"r":7.6,"v":1349},"5":{"r":7.5,"v":1311},"6":{"r":7.5,"v":1306},"7":{"r":7.6,"v":1322},"8":{"r":7.9,"v":1476}},"3":{"1":{"r":7.5,"v":1115},"2":{"r":7.6,"v":1018},"3":{"r":7.4,"v":976},"4":{"r":7.5,"v":951},"5":{"r":7.7,"v":924},"6":{"r":7.6,"v":923},"7":{"r":8.0,"v":982},"8":{"r":7.6,"v":1092}}}}