{"id":"tt12677870","title":"Law & Order: Organized Crime","votes":12500,"seasons":{"1":{"1":{"r":7.8,"v":861},"2":{"r":7.8,"v":634},"3":{"r":7.8,"v":553},"4":{"r":8.0,"v":547},"5":{"r":8.2,"v":524},"6":{"r":8.2,"v":484},"7":{"r":8.4,"v":475},"8":{"r":8.4,"v":506}},"2":{"1":{"r":8.0,"v":484},"2":{"r":8.2,"v":429},"3":{"r":8.4,"v":429},"4":{"r":8.2,"v":392},"5":{"r":8.4,"v":411},"6":{"r":8.3,"v":369},"7":{"r":8.5,"v":385},"8":{"r":8.6,"v":446},"9":{"r":8.2,"v":422},"10":{"r":7.7,"v":351},"11":{"r":7.6,"v":333},"12":{"r":7.9,"v":339},"13":{"r":7.7,"v":332},"14":{"r":7.8,"v":354},"15":{"r":8.0,"v":323},"16":{"r":8.0,"v":299},"17":{"r":8.1,"v":288},"18":{"r":8.1,"v":291},"19":{"r":7.8,"v":274},"20":{"r":8.1,"v":303},"21":{"r":8.4,"v":278},"22":{"r":8.6,"v":309}},"3":{"1":{"r":8.1,"v":439},"2":{"r":8.2,"v":322},"3":{"r":7.9,"v":299},"4":{"r":8.1,"v":280},"5":{"r":8.2,"v":281},"6":{"r":7.8,"v":265},"7":{"r":7.5,"v":276},"8":{"r":7.9,"v":274},"9":{"r":8.2,"v":282},"10":{"r":7.7,"v":268},"11":{"r":7.8,"v":264},"12":{"r":7.9,"v":278},"13":{"r":8.1,"v":275},"14":{"r":7.9,"v":268},"15":{"r":7.6,"v":261},"16":{"r":7.7,"v":257},"17":{"r":7.9,"v":262},"18":{"r":7.6,"v":270},"19":{"r":8.0,"v":275},"20":{"r":7.7,"v":255},"21":{"r":8.3,"v":305},"22":{"r":8.6,"v":367}},"4":{"1":{"r":8.0,"v":337},"2":{"r":8.0,"v":318},"3":{"r":7.9,"v":296},"4":{"r":8.2,"v":315},"5":{"r":8.2,"v":297},"6":{"r":8.4,"v":299},"7":{"r":8.4,"v":294},"8":{"r":8.6,"v":298},"9":{"r":8.3,"v":276},"10":{"r":8.5,"v":258},"11":{"r":8.2,"v":247},"12":{"r":8.1,"v":229},"13":{"r":8.2,"v":238}},"5":{"1":{"r":8.6,"v":301},"2":{"r":8.7,"v":297},"3":{"r":8.0,"v":235},"4":{"r":8.0,"v":220},"5":{"r":8.2,"v":218},"6":{"r":7.9,"v":213},"7":{"r":7.6,"v":186},"8":{"r":8.0,"v":172},"9":{"r":8.5,"v":185},"10":{"r":8.7,"v":201}}}}