{"id":"tt13911284","title":"Hell's Paradise","votes":29670,"seasons":{"1":{"1":{"r":8.2,"v":2629},"2":{"r":8.3,"v":2302},"3":{"r":8.5,"v":2259},"4":{"r":7.9,"v":2007},"5":{"r":7.6,"v":1872},"6":{"r":8.1,"v":1866},"7":{"r":7.8,"v":1785},"8":{"r":9.0,"v":2542},"9":{"r":9.1,"v":2311},"10":{"r":7.8,"v":1711},"11":{"r":8.6,"v":1816},"12":{"r":8.9,"v":1900},"13":{"r":8.8,"v":1895}},"2":{"1":{"r":8.2,"v":2038},"2":{"r":8.5,"v":1806},"4":{"r":8.4,"v":1470},"5":{"r":8.2,"v":1419},"3":{"r":8.4,"v":1525},"6":{"r":9.1,"v":1615},"7":{"r":9.3,"v":1936},"8":{"r":9.2,"v":1624},"9":{"r":8.7,"v":1241},"10":{"r":8.9,"v":1291},"11":{"r":9.1,"v":1117},"12":{"r":8.7,"v":999}}}}