{"id":"tt14016500","title":"The Summer I Turned Pretty","votes":71779,"seasons":{"1":{"1":{"r":7.3,"v":1648},"2":{"r":7.3,"v":1265},"3":{"r":7.4,"v":1220},"4":{"r":7.6,"v":1210},"5":{"r":7.5,"v":1192},"6":{"r":7.6,"v":1219},"7":{"r":8.3,"v":1593}},"2":{"1":{"r":7.3,"v":1159},"2":{"r":7.7,"v":1119},"3":{"r":7.8,"v":1092},"4":{"r":7.1,"v":1093},"5":{"r":7.3,"v":1018},"6":{"r":7.9,"v":1063},"7":{"r":7.8,"v":954},"8":{"r":7.7,"v":1052}},"3":{"1":{"r":7.2,"v":1298},"2":{"r":7.5,"v":1382},"3":{"r":6.6,"v":1308},"4":{"r":6.9,"v":1172},"5":{"r":8.9,"v":2958},"6":{"r":7.9,"v":1395},"7":{"r":8.5,"v":1689},"8":{"r":8.9,"v":1930},"9":{"r":5.6,"v":2111},"10":{"r":7.2,"v":1281},"11":{"r":8.5,"v":2144}}}}