{"id":"tt18699118","title":"Alert: Missing Persons Unit","votes":4750,"seasons":{"1":{"1":{"r":6.4,"v":400},"2":{"r":6.5,"v":331},"3":{"r":6.5,"v":300},"4":{"r":7.0,"v":255},"5":{"r":6.8,"v":233},"6":{"r":6.7,"v":227},"7":{"r":7.1,"v":213},"8":{"r":7.2,"v":213},"9":{"r":7.4,"v":207},"10":{"r":7.3,"v":227}},"2":{"1":{"r":7.5,"v":188},"2":{"r":7.3,"v":173},"3":{"r":7.4,"v":148},"4":{"r":7.2,"v":148},"5":{"r":7.6,"v":137},"6":{"r":7.1,"v":136},"7":{"r":7.3,"v":129},"8":{"r":7.5,"v":120},"9":{"r":7.8,"v":117},"10":{"r":8.0,"v":146}},"3":{"1":{"r":7.4,"v":127},"2":{"r":7.2,"v":143},"3":{"r":7.1,"v":113},"4":{"r":7.5,"v":107},"5":{"r":7.3,"v":114},"6":{"r":7.3,"v":102},"7":{"r":7.8,"v":94},"8":{"r":8.0,"v":97},"9":{"r":7.2,"v":88},"10":{"r":7.5,"v":97}}}}