{"id":"tt2215842","title":"Father Brown","votes":17526,"seasons":{"8":{"1":{"r":7.8,"v":469},"10":{"r":8.7,"v":507},"7":{"r":7.7,"v":363},"8":{"r":7.6,"v":377},"9":{"r":7.4,"v":358},"5":{"r":7.9,"v":412},"2":{"r":7.4,"v":418},"3":{"r":7.8,"v":411},"4":{"r":6.9,"v":440},"6":{"r":7.5,"v":386}},"9":{"1":{"r":7.7,"v":465},"10":{"r":8.0,"v":398},"9":{"r":7.3,"v":346},"2":{"r":7.7,"v":408},"3":{"r":7.8,"v":392},"4":{"r":6.9,"v":378},"5":{"r":8.3,"v":440},"6":{"r":7.5,"v":405},"7":{"r":6.6,"v":410},"8":{"r":7.4,"v":380}},"10":{"1":{"r":7.8,"v":445},"2":{"r":7.4,"v":380},"3":{"r":7.3,"v":356},"4":{"r":7.1,"v":381},"5":{"r":7.6,"v":339},"6":{"r":7.6,"v":341},"7":{"r":7.4,"v":330},"9":{"r":7.0,"v":315},"10":{"r":7.7,"v":328},"8":{"r":7.0,"v":324}},"1":{"2":{"r":7.3,"v":652},"1":{"r":7.3,"v":836},"10":{"r":7.8,"v":553},"5":{"r":7.1,"v":575},"3":{"r":7.3,"v":631},"4":{"r":7.6,"v":585},"6":{"r":7.9,"v":622},"7":{"r":7.5,"v":556},"8":{"r":7.6,"v":538},"9":{"r":7.4,"v":523}},"11":{"1":{"r":7.2,"v":319},"2":{"r":8.0,"v":326},"3":{"r":7.7,"v":300},"4":{"r":7.2,"v":282},"5":{"r":8.0,"v":324},"6":{"r":7.3,"v":297},"7":{"r":7.8,"v":269},"8":{"r":7.4,"v":264},"9":{"r":7.2,"v":265},"10":{"r":7.9,"v":257}},"12":{"1":{"r":7.4,"v":271},"2":{"r":7.3,"v":249},"3":{"r":6.9,"v":266},"4":{"r":7.5,"v":238},"5":{"r":7.9,"v":244},"6":{"r":7.2,"v":211},"7":{"r":7.2,"v":217},"8":{"r":7.3,"v":205},"9":{"r":7.5,"v":192},"10":{"r":8.0,"v":221}},"2":{"1":{"r":7.7,"v":539},"2":{"r":7.6,"v":494},"3":{"r":7.6,"v":530},"4":{"r":7.6,"v":496},"5":{"r":7.6,"v":514},"6":{"r":7.9,"v":513},"7":{"r":7.3,"v":476},"8":{"r":7.6,"v":480},"9":{"r":7.6,"v":468},"10":{"r":7.8,"v":474}},"13":{"1":{"r":7.7,"v":159},"2":{"r":7.3,"v":131},"5":{"r":8.0,"v":96},"6":{"r":7.7,"v":74},"7":{"r":7.0,"v":83},"8":{"r":7.3,"v":74},"9":{"r":6.7,"v":53},"10":{"r":7.6,"v":50},"4":{"r":7.1,"v":126},"3":{"r":7.7,"v":141}},"3":{"1":{"r":7.7,"v":482},"2":{"r":7.7,"v":512},"7":{"r":7.5,"v":454},"3":{"r":7.2,"v":486},"4":{"r":7.5,"v":459},"5":{"r":8.0,"v":514},"6":{"r":7.7,"v":469},"8":{"r":6.9,"v":552},"9":{"r":7.9,"v":473},"10":{"r":8.0,"v":467},"11":{"r":7.7,"v":436},"12":{"r":7.1,"v":428},"13":{"r":7.7,"v":411},"14":{"r":7.7,"v":429},"15":{"r":8.5,"v":514}},"4":{"1":{"r":7.6,"v":503},"2":{"r":7.7,"v":457},"3":{"r":7.7,"v":446},"4":{"r":7.7,"v":461},"5":{"r":8.0,"v":480},"7":{"r":7.1,"v":459},"8":{"r":7.5,"v":426},"6":{"r":7.9,"v":457},"9":{"r":7.4,"v":405},"10":{"r":7.4,"v":444}},"5":{"1":{"r":8.3,"v":608},"3":{"r":7.3,"v":491},"4":{"r":7.2,"v":434},"2":{"r":8.2,"v":589},"5":{"r":6.7,"v":514},"6":{"r":7.9,"v":448},"7":{"r":8.0,"v":484},"9":{"r":7.7,"v":425},"8":{"r":7.6,"v":439},"10":{"r":7.8,"v":431},"11":{"r":8.4,"v":503},"12":{"r":7.7,"v":449},"14":{"r":7.4,"v":383},"13":{"r":7.3,"v":398},"15":{"r":8.2,"v":453}},"6":{"3":{"r":7.8,"v":437},"1":{"r":8.3,"v":515},"2":{"r":7.8,"v":465},"4":{"r":7.5,"v":429},"5":{"r":8.1,"v":464},"6":{"r":8.1,"v":440},"7":{"r":7.3,"v":423},"8":{"r":7.5,"v":388},"9":{"r":7.4,"v":414},"10":{"r":8.2,"v":429}},"7":{"1":{"r":8.2,"v":537},"2":{"r":7.3,"v":458},"3":{"r":7.5,"v":436},"4":{"r":7.2,"v":457},"5":{"r":7.8,"v":428},"6":{"r":8.3,"v":446},"7":{"r":7.3,"v":393},"8":{"r":6.8,"v":416},"9":{"r":7.3,"v":375},"10":{"r":8.4,"v":431}}}}