{"id":"tt2356777","title":"True Detective","votes":751991,"seasons":{"4":{"1":{"r":7.1,"v":20503},"2":{"r":6.8,"v":14776},"3":{"r":6.3,"v":13425},"4":{"r":6.2,"v":12837},"5":{"r":6.8,"v":12464},"6":{"r":5.4,"v":17369}},"1":{"1":{"r":8.9,"v":37876},"2":{"r":8.8,"v":32569},"4":{"r":9.6,"v":44606},"3":{"r":9.1,"v":31613},"5":{"r":9.5,"v":34840},"6":{"r":9.2,"v":29825},"7":{"r":9.2,"v":29385},"8":{"r":9.6,"v":41360}},"2":{"1":{"r":7.5,"v":17599},"3":{"r":7.3,"v":11538},"2":{"r":7.6,"v":12824},"4":{"r":8.1,"v":12256},"5":{"r":7.6,"v":10489},"7":{"r":8.5,"v":12506},"8":{"r":8.0,"v":14329},"6":{"r":8.2,"v":11147}},"3":{"1":{"r":8.5,"v":12074},"4":{"r":8.0,"v":8374},"2":{"r":8.0,"v":9594},"3":{"r":7.7,"v":8631},"6":{"r":8.3,"v":8183},"5":{"r":8.3,"v":8475},"7":{"r":8.5,"v":8417},"8":{"r":8.0,"v":10586}}}}