{"id":"tt27954448","title":"Law & Order Toronto: Criminal Intent","votes":2282,"seasons":{"1":{"1":{"r":7.3,"v":450},"2":{"r":7.5,"v":356},"3":{"r":7.2,"v":330},"4":{"r":7.2,"v":273},"5":{"r":7.2,"v":237},"6":{"r":7.3,"v":223},"7":{"r":7.4,"v":222},"9":{"r":7.4,"v":198},"8":{"r":7.0,"v":201},"10":{"r":7.5,"v":184}},"2":{"1":{"r":7.2,"v":177},"2":{"r":7.2,"v":140},"3":{"r":7.2,"v":143},"4":{"r":7.5,"v":139},"5":{"r":7.3,"v":124},"6":{"r":7.2,"v":119},"7":{"r":7.4,"v":129},"8":{"r":7.6,"v":128},"9":{"r":7.3,"v":121},"10":{"r":7.8,"v":129}},"3":{"1":{"r":7.6,"v":77},"4":{"r":8.0,"v":49},"5":{"r":8.1,"v":38},"2":{"r":7.7,"v":72},"3":{"r":7.4,"v":57}}}}