{"id":"tt2707408","title":"Narcos","votes":525293,"seasons":{"1":{"1":{"r":8.8,"v":10764},"3":{"r":8.4,"v":7525},"2":{"r":8.4,"v":8206},"4":{"r":8.6,"v":7387},"6":{"r":9.0,"v":7660},"5":{"r":8.3,"v":6869},"7":{"r":8.5,"v":6609},"8":{"r":8.9,"v":7091},"10":{"r":8.8,"v":6964},"9":{"r":8.6,"v":6500}},"2":{"1":{"r":8.3,"v":6085},"2":{"r":8.5,"v":5808},"3":{"r":8.6,"v":5701},"4":{"r":9.3,"v":7432},"5":{"r":8.5,"v":5441},"6":{"r":9.1,"v":6353},"7":{"r":8.6,"v":5553},"8":{"r":8.7,"v":5522},"9":{"r":8.5,"v":5490},"10":{"r":9.4,"v":8838}},"3":{"1":{"r":7.8,"v":5379},"2":{"r":7.9,"v":4597},"3":{"r":8.0,"v":4505},"4":{"r":8.9,"v":4841},"5":{"r":8.4,"v":4386},"6":{"r":8.7,"v":4532},"7":{"r":8.9,"v":4600},"8":{"r":8.7,"v":4464},"9":{"r":9.3,"v":5309},"10":{"r":9.1,"v":5107}}}}