{"id":"tt28919914","title":"The 100 Girlfriends Who Really, Really, Really, Really, REALLY Love You","votes":3853,"seasons":{"1":{"1":{"r":7.5,"v":437},"2":{"r":7.5,"v":411},"3":{"r":7.5,"v":424},"4":{"r":7.4,"v":433},"5":{"r":7.5,"v":391},"7":{"r":7.2,"v":331},"6":{"r":7.4,"v":403},"8":{"r":7.4,"v":381},"9":{"r":7.5,"v":327},"10":{"r":7.5,"v":382},"11":{"r":7.3,"v":454},"12":{"r":7.3,"v":416}},"2":{"1":{"r":7.5,"v":352},"2":{"r":7.3,"v":278},"3":{"r":7.0,"v":264},"4":{"r":6.9,"v":265},"5":{"r":6.8,"v":295},"6":{"r":7.1,"v":297},"7":{"r":7.0,"v":241},"8":{"r":6.7,"v":232},"9":{"r":6.5,"v":231},"10":{"r":6.8,"v":238},"11":{"r":7.1,"v":239},"12":{"r":7.4,"v":254}}}}