{"id":"tt32484114","title":"The Double","votes":1977,"seasons":{"1":{"1":{"r":9.0,"v":41},"2":{"r":9.0,"v":43},"3":{"r":8.9,"v":34},"4":{"r":8.8,"v":31},"5":{"r":9.5,"v":31},"6":{"r":8.6,"v":28},"7":{"r":9.0,"v":28},"8":{"r":8.9,"v":26},"9":{"r":9.0,"v":27},"10":{"r":8.9,"v":27},"11":{"r":9.1,"v":31},"12":{"r":9.0,"v":28},"13":{"r":9.2,"v":31},"14":{"r":8.7,"v":26},"15":{"r":8.5,"v":26},"16":{"r":8.7,"v":27},"17":{"r":8.7,"v":27},"18":{"r":8.6,"v":25},"19":{"r":8.8,"v":27},"20":{"r":8.6,"v":19},"21":{"r":7.8,"v":19},"22":{"r":8.1,"v":19},"23":{"r":8.5,"v":18},"24":{"r":8.7,"v":21},"25":{"r":8.5,"v":18},"26":{"r":8.8,"v":19},"27":{"r":8.4,"v":19},"28":{"r":8.7,"v":21},"29":{"r":8.3,"v":20},"30":{"r":8.0,"v":22},"31":{"r":8.2,"v":21},"32":{"r":8.2,"v":20},"33":{"r":8.1,"v":22},"34":{"r":8.3,"v":22},"35":{"r":7.9,"v":20},"36":{"r":7.9,"v":18},"37":{"r":7.9,"v":19},"38":{"r":7.8,"v":20},"39":{"r":7.7,"v":19},"40":{"r":8.1,"v":26}}}}