{"id":"tt3322312","title":"Daredevil","votes":527492,"seasons":{"1":{"1":{"r":8.4,"v":18545},"2":{"r":8.9,"v":17857},"3":{"r":8.2,"v":15104},"4":{"r":8.6,"v":14664},"5":{"r":8.7,"v":14198},"6":{"r":8.9,"v":14526},"7":{"r":8.5,"v":13988},"8":{"r":8.9,"v":14134},"9":{"r":9.1,"v":14552},"10":{"r":8.4,"v":13466},"12":{"r":8.6,"v":12963},"11":{"r":8.7,"v":13312},"13":{"r":9.3,"v":16683}},"2":{"1":{"r":8.8,"v":13778},"2":{"r":8.6,"v":12428},"3":{"r":9.4,"v":16282},"4":{"r":9.4,"v":15503},"5":{"r":8.1,"v":13401},"7":{"r":8.5,"v":10949},"6":{"r":8.4,"v":11069},"9":{"r":9.4,"v":13976},"10":{"r":9.0,"v":11443},"12":{"r":8.8,"v":10945},"11":{"r":8.6,"v":10710},"13":{"r":9.1,"v":13024},"8":{"r":9.0,"v":11875}},"3":{"1":{"r":8.2,"v":10462},"2":{"r":8.5,"v":9812},"3":{"r":8.4,"v":9463},"4":{"r":9.5,"v":15415},"5":{"r":8.8,"v":10172},"6":{"r":9.5,"v":12433},"7":{"r":8.7,"v":9547},"8":{"r":9.0,"v":9701},"9":{"r":9.1,"v":9660},"10":{"r":8.6,"v":10403},"11":{"r":9.1,"v":9546},"12":{"r":9.3,"v":10298},"13":{"r":9.6,"v":14907}}}}