{"id":"tt3501584","title":"iZombie","votes":78895,"seasons":{"1":{"1":{"r":8.0,"v":2571},"2":{"r":7.8,"v":1966},"3":{"r":7.7,"v":1746},"4":{"r":7.7,"v":1685},"6":{"r":7.9,"v":1548},"5":{"r":7.9,"v":1635},"7":{"r":7.8,"v":1468},"9":{"r":8.3,"v":1515},"10":{"r":8.0,"v":1359},"11":{"r":8.5,"v":1493},"12":{"r":8.7,"v":1548},"8":{"r":7.9,"v":1442},"13":{"r":8.8,"v":1671}},"2":{"1":{"r":8.0,"v":1293},"2":{"r":8.1,"v":1211},"3":{"r":7.9,"v":1166},"4":{"r":7.9,"v":1138},"6":{"r":7.9,"v":1079},"8":{"r":8.0,"v":1054},"5":{"r":8.0,"v":1102},"9":{"r":8.1,"v":1076},"7":{"r":7.9,"v":1076},"10":{"r":8.0,"v":1041},"19":{"r":9.1,"v":1422},"12":{"r":7.9,"v":982},"11":{"r":8.3,"v":1086},"13":{"r":8.0,"v":996},"14":{"r":8.4,"v":1044},"15":{"r":8.3,"v":1001},"16":{"r":8.4,"v":1020},"17":{"r":8.3,"v":1011},"18":{"r":9.0,"v":1236}},"3":{"1":{"r":7.9,"v":965},"3":{"r":7.6,"v":836},"4":{"r":7.8,"v":820},"5":{"r":8.5,"v":905},"6":{"r":7.8,"v":797},"2":{"r":8.3,"v":970},"8":{"r":7.8,"v":779},"7":{"r":7.8,"v":786},"12":{"r":8.4,"v":823},"13":{"r":8.6,"v":868},"10":{"r":8.2,"v":787},"9":{"r":8.2,"v":837},"11":{"r":8.1,"v":776}},"4":{"1":{"r":7.5,"v":826},"2":{"r":7.5,"v":742},"3":{"r":7.6,"v":736},"4":{"r":7.6,"v":727},"5":{"r":7.8,"v":721},"6":{"r":7.8,"v":724},"7":{"r":7.5,"v":692},"8":{"r":7.5,"v":684},"9":{"r":7.8,"v":678},"10":{"r":7.7,"v":665},"11":{"r":8.2,"v":730},"13":{"r":8.4,"v":783},"12":{"r":7.9,"v":669}},"5":{"1":{"r":7.4,"v":690},"2":{"r":7.4,"v":612},"3":{"r":7.9,"v":660},"4":{"r":7.3,"v":597},"5":{"r":7.7,"v":587},"6":{"r":7.6,"v":581},"9":{"r":7.6,"v":557},"8":{"r":7.4,"v":568},"7":{"r":7.6,"v":570},"11":{"r":7.5,"v":567},"10":{"r":7.8,"v":589},"12":{"r":8.3,"v":618},"13":{"r":8.2,"v":813}}}}