{"id":"tt3815412","title":"Our Girl","votes":5561,"seasons":{"2":{"0":{"r":8.8,"v":36},"1":{"r":7.3,"v":169},"2":{"r":7.7,"v":128},"3":{"r":6.9,"v":94},"4":{"r":7.1,"v":106},"5":{"r":6.9,"v":115}},"1":{"1":{"r":7.8,"v":283},"2":{"r":7.9,"v":227},"3":{"r":8.1,"v":212},"4":{"r":8.1,"v":207},"5":{"r":8.3,"v":203}},"3":{"4":{"r":7.8,"v":95},"3":{"r":7.1,"v":77},"9":{"r":7.4,"v":57},"10":{"r":7.0,"v":60},"1":{"r":6.7,"v":117},"2":{"r":6.8,"v":86},"5":{"r":7.4,"v":75},"6":{"r":7.8,"v":66},"7":{"r":7.6,"v":59},"8":{"r":7.5,"v":62},"11":{"r":6.8,"v":52},"12":{"r":7.4,"v":54}},"4":{"1":{"r":7.5,"v":65},"2":{"r":8.0,"v":45},"3":{"r":8.1,"v":49},"4":{"r":8.0,"v":46},"5":{"r":7.8,"v":42},"6":{"r":8.2,"v":49}}}}