{"id":"tt4219258","title":"The Testament of Sister New Devil","votes":4200,"seasons":{"2":{"11":{"r":7.6,"v":61},"1":{"r":8.1,"v":109},"2":{"r":7.7,"v":87},"3":{"r":7.6,"v":90},"4":{"r":7.3,"v":83},"5":{"r":7.5,"v":81},"6":{"r":7.5,"v":74},"7":{"r":7.5,"v":76},"8":{"r":7.6,"v":72},"9":{"r":7.7,"v":72},"10":{"r":7.7,"v":78}},"1":{"1":{"r":7.0,"v":162},"2":{"r":6.9,"v":118},"3":{"r":7.5,"v":114},"4":{"r":7.2,"v":109},"5":{"r":7.0,"v":108},"6":{"r":7.3,"v":107},"7":{"r":7.1,"v":103},"8":{"r":7.3,"v":106},"9":{"r":7.6,"v":108},"10":{"r":7.5,"v":102},"11":{"r":7.4,"v":100},"12":{"r":7.6,"v":102},"13":{"r":8.4,"v":112}}}}