{"id":"tt4219258","title":"The Testament of Sister New Devil","votes":4179,"seasons":{"2":{"11":{"r":7.5,"v":60},"1":{"r":8.1,"v":107},"2":{"r":7.6,"v":85},"3":{"r":7.5,"v":88},"4":{"r":7.3,"v":81},"5":{"r":7.4,"v":80},"6":{"r":7.5,"v":73},"7":{"r":7.5,"v":75},"8":{"r":7.6,"v":71},"9":{"r":7.7,"v":71},"10":{"r":7.7,"v":77}},"1":{"1":{"r":7.0,"v":160},"2":{"r":7.0,"v":116},"3":{"r":7.4,"v":112},"4":{"r":7.2,"v":107},"5":{"r":7.0,"v":106},"6":{"r":7.2,"v":105},"7":{"r":7.1,"v":101},"8":{"r":7.3,"v":104},"9":{"r":7.6,"v":106},"10":{"r":7.5,"v":100},"11":{"r":7.4,"v":98},"12":{"r":7.6,"v":100},"13":{"r":8.4,"v":109}}}}