{"id":"tt5370118","title":"Konosuba: God's Blessing on This Wonderful World!","votes":20606,"seasons":{"3":{"1":{"r":7.7,"v":399},"2":{"r":7.8,"v":355},"3":{"r":7.8,"v":342},"4":{"r":7.8,"v":341},"5":{"r":8.1,"v":423},"6":{"r":8.4,"v":499},"7":{"r":7.8,"v":316},"8":{"r":8.1,"v":390},"9":{"r":7.9,"v":370},"10":{"r":8.0,"v":377},"11":{"r":8.3,"v":410},"12":{"r":7.6,"v":173},"13":{"r":7.9,"v":168}},"1":{"11":{"r":8.6,"v":103},"1":{"r":7.5,"v":700},"2":{"r":7.5,"v":617},"3":{"r":7.6,"v":591},"4":{"r":7.5,"v":571},"5":{"r":7.9,"v":605},"6":{"r":7.9,"v":581},"7":{"r":7.5,"v":532},"8":{"r":7.5,"v":524},"9":{"r":7.9,"v":617},"10":{"r":8.1,"v":628}},"2":{"1":{"r":7.9,"v":522},"2":{"r":7.8,"v":470},"3":{"r":7.8,"v":463},"4":{"r":8.0,"v":545},"5":{"r":8.0,"v":521},"6":{"r":7.6,"v":443},"7":{"r":7.4,"v":444},"8":{"r":7.9,"v":463},"9":{"r":7.5,"v":445},"10":{"r":8.4,"v":718},"11":{"r":7.6,"v":419}}}}