{"id":"tt5420376","title":"Riverdale","votes":165532,"seasons":{"4":{"2":{"r":7.3,"v":1199},"3":{"r":6.8,"v":1193},"4":{"r":7.5,"v":1147},"5":{"r":7.2,"v":1060},"6":{"r":7.0,"v":1030},"7":{"r":7.4,"v":1068},"8":{"r":7.5,"v":1087},"9":{"r":7.2,"v":995},"11":{"r":7.0,"v":947},"10":{"r":7.1,"v":968},"12":{"r":6.8,"v":931},"13":{"r":7.3,"v":981},"14":{"r":7.9,"v":1072},"15":{"r":7.5,"v":1061},"16":{"r":8.4,"v":1391},"17":{"r":3.5,"v":3084},"18":{"r":6.7,"v":1119},"19":{"r":7.3,"v":1139},"1":{"r":9.2,"v":3198}},"5":{"1":{"r":7.1,"v":1349},"2":{"r":6.7,"v":1197},"3":{"r":8.2,"v":1472},"4":{"r":7.2,"v":1316},"5":{"r":7.3,"v":1658},"6":{"r":7.2,"v":1158},"7":{"r":6.6,"v":1018},"8":{"r":5.9,"v":1215},"9":{"r":6.2,"v":1029},"10":{"r":6.3,"v":947},"11":{"r":6.0,"v":850},"13":{"r":6.2,"v":760},"12":{"r":7.8,"v":1045},"14":{"r":6.5,"v":774},"15":{"r":4.3,"v":1109},"16":{"r":5.7,"v":655},"17":{"r":6.9,"v":754},"18":{"r":3.3,"v":1442},"19":{"r":6.3,"v":934}},"6":{"1":{"r":5.0,"v":1129},"2":{"r":4.9,"v":927},"4":{"r":5.7,"v":936},"3":{"r":5.1,"v":822},"5":{"r":7.4,"v":952},"6":{"r":6.0,"v":676},"7":{"r":6.1,"v":606},"8":{"r":6.1,"v":587},"9":{"r":6.3,"v":583},"10":{"r":6.0,"v":551},"11":{"r":6.4,"v":618},"12":{"r":6.1,"v":551},"13":{"r":6.4,"v":533},"14":{"r":6.4,"v":547},"15":{"r":6.1,"v":530},"16":{"r":5.9,"v":522},"17":{"r":5.7,"v":559},"18":{"r":6.1,"v":545},"19":{"r":6.7,"v":572},"20":{"r":6.6,"v":504},"21":{"r":6.7,"v":491},"22":{"r":6.0,"v":584}},"7":{"1":{"r":6.6,"v":581},"3":{"r":6.5,"v":470},"4":{"r":6.4,"v":422},"2":{"r":6.6,"v":489},"5":{"r":6.4,"v":460},"6":{"r":6.5,"v":420},"7":{"r":6.5,"v":397},"8":{"r":6.5,"v":394},"9":{"r":6.2,"v":395},"10":{"r":6.3,"v":377},"11":{"r":6.6,"v":381},"12":{"r":6.4,"v":378},"13":{"r":6.3,"v":379},"14":{"r":4.7,"v":536},"15":{"r":6.2,"v":374},"16":{"r":5.8,"v":379},"17":{"r":5.5,"v":376},"18":{"r":6.4,"v":368},"19":{"r":7.3,"v":420},"20":{"r":7.6,"v":687}},"1":{"1":{"r":7.5,"v":3964},"2":{"r":7.7,"v":3147},"3":{"r":7.7,"v":2996},"4":{"r":7.9,"v":2836},"5":{"r":7.7,"v":2603},"6":{"r":7.8,"v":2576},"7":{"r":7.7,"v":2440},"8":{"r":7.5,"v":2335},"9":{"r":7.5,"v":2305},"10":{"r":8.0,"v":2377},"11":{"r":8.0,"v":2267},"12":{"r":8.7,"v":2834},"13":{"r":8.5,"v":2716}},"2":{"1":{"r":7.9,"v":2369},"2":{"r":7.7,"v":1979},"3":{"r":7.6,"v":1881},"4":{"r":7.8,"v":1847},"5":{"r":8.3,"v":2125},"6":{"r":7.9,"v":1840},"7":{"r":7.9,"v":1857},"8":{"r":7.8,"v":1842},"9":{"r":8.1,"v":1850},"10":{"r":7.6,"v":1695},"11":{"r":7.2,"v":1695},"12":{"r":7.7,"v":1693},"13":{"r":8.0,"v":1686},"14":{"r":7.8,"v":1699},"15":{"r":7.6,"v":1581},"16":{"r":7.7,"v":1625},"17":{"r":7.8,"v":1617},"18":{"r":5.7,"v":2949},"19":{"r":8.2,"v":1767},"20":{"r":8.2,"v":1680},"21":{"r":8.9,"v":2636},"22":{"r":7.8,"v":1701}},"3":{"1":{"r":7.6,"v":2043},"2":{"r":7.5,"v":1694},"3":{"r":7.3,"v":1592},"5":{"r":8.0,"v":1653},"4":{"r":8.3,"v":2096},"6":{"r":7.7,"v":1482},"7":{"r":7.6,"v":1492},"8":{"r":7.8,"v":1465},"11":{"r":7.3,"v":1373},"9":{"r":6.7,"v":1485},"12":{"r":7.1,"v":1385},"10":{"r":7.3,"v":1347},"13":{"r":6.5,"v":1306},"14":{"r":6.9,"v":1241},"15":{"r":7.2,"v":1256},"16":{"r":4.2,"v":2801},"17":{"r":7.1,"v":1175},"18":{"r":7.2,"v":1175},"19":{"r":7.2,"v":1195},"20":{"r":7.6,"v":1226},"21":{"r":8.0,"v":1353},"22":{"r":8.1,"v":1679}}}}