{"id":"tt6741278","title":"Invincible","votes":326310,"seasons":{"2":{"1":{"r":8.1,"v":16125},"2":{"r":7.2,"v":14945},"3":{"r":8.1,"v":15130},"4":{"r":9.2,"v":19967},"5":{"r":8.7,"v":14655},"6":{"r":7.8,"v":13708},"7":{"r":8.7,"v":15422},"8":{"r":9.1,"v":19694}},"3":{"1":{"r":8.0,"v":16959},"2":{"r":9.1,"v":20126},"3":{"r":8.5,"v":16801},"4":{"r":9.1,"v":20693},"5":{"r":7.4,"v":17313},"6":{"r":8.7,"v":20990},"7":{"r":9.7,"v":45141},"8":{"r":9.9,"v":94235}},"4":{"1":{"r":8.3,"v":17900},"2":{"r":9.3,"v":21869},"3":{"r":8.1,"v":16786},"4":{"r":6.6,"v":23274},"5":{"r":9.8,"v":39035},"7":{"r":9.9,"v":38418},"6":{"r":9.2,"v":21447}},"1":{"1":{"r":9.0,"v":28084},"2":{"r":8.4,"v":20306},"3":{"r":8.1,"v":19097},"4":{"r":7.7,"v":18809},"5":{"r":9.1,"v":21595},"6":{"r":7.6,"v":19069},"7":{"r":9.6,"v":29177},"8":{"r":9.7,"v":36929}}}}