{"id":"tt7042146","title":"Carmen Sandiego","votes":8339,"seasons":{"3":{"1":{"r":7.8,"v":181},"2":{"r":8.0,"v":162},"3":{"r":7.8,"v":163},"4":{"r":7.9,"v":163},"5":{"r":8.7,"v":189}},"4":{"1":{"r":7.7,"v":163},"2":{"r":7.7,"v":153},"3":{"r":8.1,"v":154},"4":{"r":8.6,"v":166},"5":{"r":8.3,"v":154},"6":{"r":8.6,"v":166},"7":{"r":8.4,"v":162},"8":{"r":9.1,"v":248}},"1":{"1":{"r":7.6,"v":420},"2":{"r":8.1,"v":369},"3":{"r":7.6,"v":322},"4":{"r":7.5,"v":304},"5":{"r":7.9,"v":292},"6":{"r":7.9,"v":290},"7":{"r":8.0,"v":281},"8":{"r":7.9,"v":280},"9":{"r":8.7,"v":329}},"2":{"1":{"r":7.7,"v":234},"2":{"r":7.8,"v":222},"3":{"r":8.0,"v":221},"4":{"r":7.6,"v":216},"5":{"r":7.5,"v":210},"6":{"r":7.8,"v":205},"7":{"r":7.8,"v":207},"8":{"r":8.0,"v":206},"9":{"r":7.9,"v":205},"10":{"r":8.5,"v":224}}}}