{"id":"tt7230846","title":"No Activity","votes":1715,"seasons":{"3":{"1":{"r":7.2,"v":45},"2":{"r":7.6,"v":40},"3":{"r":7.7,"v":32},"4":{"r":7.5,"v":33},"5":{"r":7.7,"v":29},"6":{"r":7.6,"v":31},"7":{"r":6.9,"v":29},"8":{"r":8.3,"v":44}},"4":{"1":{"r":5.1,"v":59},"2":{"r":7.1,"v":26},"3":{"r":7.2,"v":22},"4":{"r":7.0,"v":20},"5":{"r":7.4,"v":19},"6":{"r":7.2,"v":16},"7":{"r":7.9,"v":19},"8":{"r":7.4,"v":20}},"1":{"1":{"r":7.2,"v":96},"2":{"r":7.4,"v":76},"3":{"r":7.4,"v":62},"4":{"r":7.7,"v":60},"5":{"r":7.6,"v":56},"6":{"r":8.2,"v":51},"7":{"r":7.8,"v":43},"8":{"r":8.2,"v":43}},"2":{"8":{"r":8.6,"v":49},"1":{"r":7.8,"v":47},"2":{"r":8.3,"v":54},"3":{"r":8.2,"v":44},"4":{"r":8.3,"v":43},"5":{"r":8.4,"v":42},"6":{"r":8.4,"v":41},"7":{"r":8.4,"v":40}}}}