{"id":"tt7671070","title":"Industry","votes":26716,"seasons":{"1":{"1":{"r":7.3,"v":1404},"2":{"r":7.2,"v":1061},"3":{"r":7.2,"v":948},"4":{"r":7.9,"v":977},"5":{"r":7.4,"v":834},"6":{"r":7.7,"v":871},"7":{"r":7.4,"v":797},"8":{"r":7.9,"v":876}},"2":{"1":{"r":7.2,"v":802},"2":{"r":8.0,"v":800},"3":{"r":7.8,"v":728},"4":{"r":7.3,"v":674},"5":{"r":7.4,"v":712},"6":{"r":7.9,"v":674},"7":{"r":8.3,"v":713},"8":{"r":8.7,"v":878}},"3":{"1":{"r":8.5,"v":1035},"4":{"r":9.0,"v":1356},"3":{"r":8.6,"v":924},"5":{"r":8.2,"v":830},"8":{"r":9.2,"v":1382},"2":{"r":8.5,"v":901},"6":{"r":8.9,"v":992},"7":{"r":8.9,"v":915}},"4":{"1":{"r":8.0,"v":829},"2":{"r":8.8,"v":1155},"3":{"r":8.0,"v":617},"4":{"r":8.4,"v":685},"7":{"r":8.5,"v":607},"6":{"r":9.3,"v":1126},"5":{"r":8.4,"v":622},"8":{"r":8.5,"v":575}}}}