{"id":"tt7908628","title":"What We Do in the Shadows","votes":126040,"seasons":{"2":{"1":{"r":8.3,"v":2861},"2":{"r":7.9,"v":2731},"10":{"r":8.7,"v":2618},"3":{"r":8.1,"v":2664},"4":{"r":8.6,"v":2843},"5":{"r":9.0,"v":3416},"6":{"r":8.8,"v":3553},"7":{"r":7.9,"v":2452},"8":{"r":7.9,"v":2380},"9":{"r":8.0,"v":2458}},"3":{"1":{"r":8.0,"v":2367},"3":{"r":7.6,"v":2237},"9":{"r":8.5,"v":2105},"2":{"r":8.4,"v":2547},"4":{"r":8.5,"v":2397},"5":{"r":7.5,"v":2058},"6":{"r":8.6,"v":2431},"7":{"r":7.6,"v":2087},"10":{"r":8.6,"v":2249},"8":{"r":8.3,"v":2245}},"4":{"1":{"r":7.6,"v":1956},"9":{"r":7.5,"v":1746},"10":{"r":8.2,"v":1673},"2":{"r":7.7,"v":1880},"3":{"r":7.5,"v":1812},"4":{"r":8.1,"v":1890},"5":{"r":8.5,"v":2178},"6":{"r":8.1,"v":1765},"7":{"r":8.0,"v":1788},"8":{"r":8.4,"v":2099}},"5":{"1":{"r":7.9,"v":1738},"2":{"r":8.0,"v":1654},"3":{"r":8.6,"v":2034},"4":{"r":8.0,"v":1695},"5":{"r":8.7,"v":1971},"6":{"r":8.4,"v":1642},"7":{"r":7.4,"v":1560},"8":{"r":8.0,"v":1462},"9":{"r":8.0,"v":1373},"10":{"r":8.2,"v":1498}},"6":{"1":{"r":7.4,"v":1294},"2":{"r":7.7,"v":1243},"3":{"r":8.0,"v":1259},"5":{"r":7.5,"v":1160},"4":{"r":7.5,"v":1161},"6":{"r":7.9,"v":1151},"7":{"r":7.4,"v":1093},"8":{"r":7.5,"v":1099},"9":{"r":8.5,"v":1261},"10":{"r":7.8,"v":1005},"11":{"r":8.2,"v":1443}},"1":{"2":{"r":7.8,"v":3710},"3":{"r":8.1,"v":3568},"4":{"r":7.8,"v":3275},"6":{"r":8.8,"v":3777},"5":{"r":8.0,"v":3218},"7":{"r":9.2,"v":5204},"8":{"r":8.1,"v":2940},"9":{"r":7.8,"v":2876},"10":{"r":8.3,"v":2873},"1":{"r":7.9,"v":4351}}}}