{"id":"tt8594324","title":"Ghosts","votes":32806,"seasons":{"2":{"1":{"r":7.8,"v":863},"7":{"r":8.2,"v":850},"6":{"r":8.4,"v":860},"5":{"r":8.6,"v":968},"2":{"r":7.8,"v":835},"4":{"r":8.1,"v":831},"3":{"r":8.2,"v":807}},"3":{"1":{"r":7.9,"v":700},"6":{"r":8.6,"v":746},"2":{"r":7.7,"v":661},"3":{"r":8.2,"v":682},"4":{"r":7.6,"v":638},"5":{"r":8.1,"v":640},"7":{"r":8.1,"v":583}},"4":{"1":{"r":7.6,"v":564},"2":{"r":7.8,"v":524},"3":{"r":8.0,"v":512},"4":{"r":8.5,"v":613},"5":{"r":7.5,"v":483},"6":{"r":7.8,"v":477},"7":{"r":8.7,"v":574}},"5":{"1":{"r":8.1,"v":497},"2":{"r":7.6,"v":431},"3":{"r":8.2,"v":445},"4":{"r":7.9,"v":435},"5":{"r":8.6,"v":529},"6":{"r":8.3,"v":450},"0":{"r":7.9,"v":205},"7":{"r":8.3,"v":574}},"1":{"1":{"r":7.5,"v":1221},"2":{"r":7.8,"v":1075},"3":{"r":7.8,"v":996},"4":{"r":7.8,"v":955},"5":{"r":7.9,"v":943},"6":{"r":7.8,"v":901}}}}