{"id":"tt8593252","title":"Coroner","votes":6439,"seasons":{"2":{"1":{"r":7.2,"v":226},"2":{"r":7.2,"v":209},"8":{"r":7.5,"v":194},"5":{"r":7.4,"v":204},"6":{"r":7.4,"v":205},"3":{"r":7.4,"v":198},"4":{"r":7.5,"v":199},"7":{"r":7.4,"v":187}},"3":{"3":{"r":7.2,"v":157},"4":{"r":7.3,"v":147},"6":{"r":7.1,"v":166},"1":{"r":7.2,"v":207},"2":{"r":7.2,"v":159},"5":{"r":7.4,"v":155},"7":{"r":7.2,"v":148},"8":{"r":7.3,"v":143},"9":{"r":7.5,"v":151},"10":{"r":7.5,"v":155}},"4":{"1":{"r":7.5,"v":161},"2":{"r":7.4,"v":128},"3":{"r":7.3,"v":120},"4":{"r":7.5,"v":120},"5":{"r":7.3,"v":114},"6":{"r":7.5,"v":107},"7":{"r":7.3,"v":102},"8":{"r":6.5,"v":115},"9":{"r":7.6,"v":98},"10":{"r":7.6,"v":102},"11":{"r":7.7,"v":108},"12":{"r":5.2,"v":185}},"1":{"5":{"r":7.3,"v":306},"6":{"r":7.3,"v":289},"1":{"r":6.9,"v":446},"2":{"r":7.2,"v":356},"3":{"r":7.2,"v":334},"4":{"r":7.5,"v":316},"7":{"r":7.6,"v":267},"8":{"r":7.5,"v":252}}}}