{"id":"tt8740790","title":"Bridgerton","votes":226353,"seasons":{"1":{"1":{"r":7.3,"v":5314},"2":{"r":7.6,"v":4583},"4":{"r":7.9,"v":4349},"3":{"r":7.7,"v":4376},"5":{"r":8.1,"v":4559},"6":{"r":7.6,"v":4173},"7":{"r":7.7,"v":4033},"8":{"r":8.1,"v":4407}},"2":{"1":{"r":7.6,"v":4259},"2":{"r":7.6,"v":3903},"5":{"r":8.1,"v":3953},"6":{"r":7.9,"v":3908},"3":{"r":8.2,"v":4250},"4":{"r":8.1,"v":3996},"7":{"r":8.2,"v":4005},"8":{"r":8.5,"v":4731}},"3":{"1":{"r":7.8,"v":5006},"7":{"r":7.6,"v":4017},"8":{"r":7.7,"v":4618},"3":{"r":7.9,"v":4577},"2":{"r":8.0,"v":4603},"4":{"r":8.6,"v":5408},"5":{"r":8.2,"v":4195},"6":{"r":7.8,"v":3959}},"4":{"1":{"r":8.0,"v":3623},"2":{"r":8.1,"v":3252},"3":{"r":8.3,"v":3274},"4":{"r":8.4,"v":3343},"5":{"r":8.2,"v":2389},"6":{"r":8.3,"v":2320},"7":{"r":8.7,"v":2679},"8":{"r":8.7,"v":2788}}}}