{"id":"tt8806524","title":"Star Trek: Picard","votes":101192,"seasons":{"1":{"9":{"r":7.3,"v":4442},"10":{"r":7.6,"v":5217},"1":{"r":8.2,"v":8270},"2":{"r":7.3,"v":6325},"3":{"r":7.4,"v":5690},"4":{"r":7.2,"v":5381},"5":{"r":6.9,"v":5549},"6":{"r":7.7,"v":4865},"7":{"r":8.3,"v":5400},"8":{"r":7.8,"v":4611}},"2":{"1":{"r":8.0,"v":5220},"2":{"r":7.9,"v":4557},"3":{"r":7.1,"v":4133},"4":{"r":6.4,"v":4426},"5":{"r":6.6,"v":3704},"6":{"r":6.2,"v":3802},"9":{"r":5.7,"v":3845},"7":{"r":5.4,"v":4227},"10":{"r":6.8,"v":4120},"8":{"r":6.2,"v":3470}},"3":{"1":{"r":8.4,"v":6500},"3":{"r":8.4,"v":5325},"4":{"r":9.0,"v":5821},"6":{"r":8.9,"v":5333},"7":{"r":8.2,"v":4432},"2":{"r":8.2,"v":5465},"5":{"r":8.9,"v":5369},"8":{"r":8.6,"v":4718},"9":{"r":9.3,"v":7035},"10":{"r":9.4,"v":7803}}}}