{"id":"tt8962130","title":"Shrill","votes":10054,"seasons":{"2":{"1":{"r":7.1,"v":169},"8":{"r":7.1,"v":116},"2":{"r":7.2,"v":160},"3":{"r":7.3,"v":150},"4":{"r":7.0,"v":114},"5":{"r":7.4,"v":116},"6":{"r":7.8,"v":144},"7":{"r":7.4,"v":108}},"3":{"1":{"r":7.1,"v":119},"8":{"r":6.4,"v":105},"2":{"r":6.6,"v":107},"3":{"r":7.4,"v":103},"4":{"r":6.7,"v":106},"5":{"r":6.5,"v":102},"6":{"r":7.5,"v":100},"7":{"r":7.4,"v":90}},"1":{"1":{"r":7.3,"v":369},"2":{"r":7.4,"v":289},"3":{"r":7.5,"v":261},"4":{"r":8.4,"v":313},"5":{"r":7.4,"v":218},"6":{"r":7.2,"v":199}}}}